docstring_inheritance/__init__.py
docstring_inheritance/class_docstrings_inheritor.py
docstring_inheritance/griffe.py
docstring_inheritance/py.typed
docstring_inheritance/docstring_inheritors/__init__.py
docstring_inheritance/docstring_inheritors/google.py
docstring_inheritance/docstring_inheritors/numpy.py
docstring_inheritance/docstring_inheritors/bases/__init__.py
docstring_inheritance/docstring_inheritors/bases/inheritor.py
docstring_inheritance/docstring_inheritors/bases/parser.py
docstring_inheritance/docstring_inheritors/bases/renderer.py
docstring_inheritance-2.2.2.dist-info/LICENSE.txt
docstring_inheritance-2.2.2.dist-info/METADATA
docstring_inheritance-2.2.2.dist-info/WHEEL
docstring_inheritance-2.2.2.dist-info/top_level.txt
docstring_inheritance-2.2.2.dist-info/RECORD
