Metadata-Version: 2.4
Name: docstring-inheritance
Version: 2.2.2
Summary: Avoid writing and maintaining duplicated docstrings.
Author: Antoine Dechaume
License: MIT
Project-URL: Documentation, https://antoined.github.io/docstring-inheritance
Project-URL: Homepage, https://github.com/AntoineD/docstring-inheritance
Project-URL: Source, https://github.com/AntoineD/docstring-inheritance
Project-URL: Tracker, https://github.com/AntoineD/docstring-inheritance/issues
Classifier: License :: OSI Approved :: MIT License
Classifier: Operating System :: MacOS
Classifier: Operating System :: Microsoft :: Windows
Classifier: Operating System :: POSIX :: Linux
Classifier: Programming Language :: Python :: 3 :: Only
Classifier: Programming Language :: Python :: 3.9
Classifier: Programming Language :: Python :: 3.10
Classifier: Programming Language :: Python :: 3.11
Classifier: Programming Language :: Python :: 3.12
Classifier: Programming Language :: Python :: 3.13
Requires-Python: <4,>=3.9
License-File: LICENSE.txt
Provides-Extra: test
Requires-Dist: covdefaults; extra == "test"
Requires-Dist: pytest; extra == "test"
Requires-Dist: pytest-cov; extra == "test"
Dynamic: license-file
